pyriandx/__init__.py
pyriandx/__main__.py
pyriandx/cli.py
pyriandx/client.py
pyriandx/utils.py
pyriandx/json/create_case.json
pyriandx/json/create_job.json
pyriandx/json/create_job_vcf.json
pyriandx/json/create_sequencer_run.json
pyriandx-0.3.0.dist-info/LICENSE
pyriandx-0.3.0.dist-info/METADATA
pyriandx-0.3.0.dist-info/WHEEL
pyriandx-0.3.0.dist-info/entry_points.txt
pyriandx-0.3.0.dist-info/top_level.txt
pyriandx-0.3.0.dist-info/RECORD
