Metadata-Version: 2.1
Name: pyriandx
Version: 0.3.0
Summary: API client CLI/SDK for PierianDx web services
Home-page: https://github.com/umccr/pyriandx
Author: UMCCR and Contributors
Author-email: services@umccr.org
License: MIT
Project-URL: Bug Tracker, https://github.com/umccr/pyriandx/issues
Classifier: Development Status :: 5 - Production/Stable
Classifier: Programming Language :: Python :: 3
Classifier: License :: OSI Approved :: MIT License
Classifier: Operating System :: OS Independent
Requires-Python: >=3.6
License-File: LICENSE
Requires-Dist: requests
Requires-Dist: urllib3
Requires-Dist: docopt
Requires-Dist: coloredlogs
Requires-Dist: verboselogs
Requires-Dist: colorama
Provides-Extra: dev
Requires-Dist: pipdeptree ; extra == 'dev'
Requires-Dist: sphinx ; extra == 'dev'
Requires-Dist: twine ; extra == 'dev'
Requires-Dist: setuptools ; extra == 'dev'
Requires-Dist: wheel ; extra == 'dev'
Requires-Dist: build ; extra == 'dev'
Requires-Dist: pdoc3 ; extra == 'dev'
Requires-Dist: tox ; extra == 'dev'
Requires-Dist: nose2 ; extra == 'dev'
Requires-Dist: pre-commit ; extra == 'dev'
Requires-Dist: detect-secrets ; extra == 'dev'
Requires-Dist: ggshield ; extra == 'dev'
Provides-Extra: test
Requires-Dist: pytest ; extra == 'test'
Requires-Dist: pytest-cov ; extra == 'test'
Requires-Dist: flake8 ; extra == 'test'
Requires-Dist: mockito ; extra == 'test'
